setup.py
dsnd_probability_awsedp/Binomialdistribution.py
dsnd_probability_awsedp/Gaussiandistribution.py
dsnd_probability_awsedp/Generaldistribution.py
dsnd_probability_awsedp/__init__.py
dsnd_probability_awsedp.egg-info/PKG-INFO
dsnd_probability_awsedp.egg-info/SOURCES.txt
dsnd_probability_awsedp.egg-info/dependency_links.txt
dsnd_probability_awsedp.egg-info/not-zip-safe
dsnd_probability_awsedp.egg-info/top_level.txt